pdf_tools_sdk_python/__init__.py
pdf_tools_sdk_python/pdf_tools_sdk_ctypes.py
pdf_tools_sdk_python/streams.py
pdf_tools_sdk_python/utils.py
pdf_tools_sdk_python/include/PdfTools.h
pdf_tools_sdk_python/include/PdfTools_PdfTools.h
pdf_tools_sdk_python/include/PdfTools_PdfToolsCryptoProviders.h
pdf_tools_sdk_python/include/PdfTools_PdfToolsCryptoProvidersBuiltIn.h
pdf_tools_sdk_python/include/PdfTools_PdfToolsCryptoProvidersGlobalSignDss.h
pdf_tools_sdk_python/include/PdfTools_PdfToolsCryptoProvidersPkcs11.h
pdf_tools_sdk_python/include/PdfTools_PdfToolsCryptoProvidersSwisscomSigSrv.h
pdf_tools_sdk_python/include/PdfTools_PdfToolsDocumentAssembly.h
pdf_tools_sdk_python/include/PdfTools_PdfToolsGeomUnits.h
pdf_tools_sdk_python/include/PdfTools_PdfToolsImage.h
pdf_tools_sdk_python/include/PdfTools_PdfToolsImage2Pdf.h
pdf_tools_sdk_python/include/PdfTools_PdfToolsImage2PdfProfiles.h
pdf_tools_sdk_python/include/PdfTools_PdfToolsOptimization.h
pdf_tools_sdk_python/include/PdfTools_PdfToolsOptimizationProfiles.h
pdf_tools_sdk_python/include/PdfTools_PdfToolsPdf.h
pdf_tools_sdk_python/include/PdfTools_PdfToolsPdf2Image.h
pdf_tools_sdk_python/include/PdfTools_PdfToolsPdf2ImageProfiles.h
pdf_tools_sdk_python/include/PdfTools_PdfToolsPdfAConversion.h
pdf_tools_sdk_python/include/PdfTools_PdfToolsPdfAValidation.h
pdf_tools_sdk_python/include/PdfTools_PdfToolsSign.h
pdf_tools_sdk_python/include/PdfTools_PdfToolsSignatureValidation.h
pdf_tools_sdk_python/include/PdfTools_PdfToolsSignatureValidationProfiles.h
pdf_tools_sdk_python/include/PdfTools_PdfToolsSys.h
pdf_tools_sdk_python/include/PdfTools_Platform.h
pdf_tools_sdk_python/include/PdfTools_Types.h
pdf_tools_sdk_python/lib/linux-x64/libPdfToolsSdk.so
pdf_tools_sdk_python/lib/osx-arm64/libPdfToolsSdk.dylib
pdf_tools_sdk_python/lib/osx-x64/libPdfToolsSdk.dylib
pdf_tools_sdk_python/lib/win-x64/PdfToolsSdk.dll
pdf_tools_sdk_python/lib/win-x86/PdfToolsSdk.dll
pdf_tools_sdk_python-1.3.4.dist-info/METADATA
pdf_tools_sdk_python-1.3.4.dist-info/WHEEL
pdf_tools_sdk_python-1.3.4.dist-info/top_level.txt
pdf_tools_sdk_python-1.3.4.dist-info/RECORD
