Metadata-Version: 2.1
Name: pdf_tools_sdk_python
Version: 1.3.4
Summary: Python package for Pdftools SDK
